wattelse/__init__.py
wattelse/api/README.md
wattelse/api/__init__.py
wattelse/api/cert.pem
wattelse/api/common/__init__.py
wattelse/api/common/client.py
wattelse/api/common/security.py
wattelse/api/create_certificate.sh
wattelse/api/embedding/README.md
wattelse/api/embedding/__init__.py
wattelse/api/embedding/client.py
wattelse/api/embedding/config/default_config.toml
wattelse/api/embedding/config/lajavaness_config.toml
wattelse/api/embedding/config/settings.py
wattelse/api/embedding/main.py
wattelse/api/embedding/models.py
wattelse/api/embedding/routers/__init__.py
wattelse/api/embedding/routers/authentication.py
wattelse/api/embedding/routers/embeddings.py
wattelse/api/embedding/routers/info.py
wattelse/api/embedding/start.py
wattelse/api/embedding/status.py
wattelse/api/embedding/stop.py
wattelse/api/key.pem
wattelse/api/openai/README.md
wattelse/api/openai/__init__.py
wattelse/api/openai/client_openai_api.py
wattelse/api/rag_orchestrator/README.md
wattelse/api/rag_orchestrator/__init__.py
wattelse/api/rag_orchestrator/client.py
wattelse/api/rag_orchestrator/config/default_config.toml
wattelse/api/rag_orchestrator/config/settings.py
wattelse/api/rag_orchestrator/main.py
wattelse/api/rag_orchestrator/models.py
wattelse/api/rag_orchestrator/rag_sessions.py
wattelse/api/rag_orchestrator/routers/__init__.py
wattelse/api/rag_orchestrator/routers/authentication.py
wattelse/api/rag_orchestrator/routers/documents.py
wattelse/api/rag_orchestrator/routers/info.py
wattelse/api/rag_orchestrator/routers/rag_query.py
wattelse/api/rag_orchestrator/routers/sessions.py
wattelse/api/rag_orchestrator/start.py
wattelse/api/rag_orchestrator/status.py
wattelse/api/rag_orchestrator/stop.py
wattelse/api/rag_orchestrator/utils.py
wattelse/api/vllm/README.md
wattelse/api/vllm/config/default_config.toml
wattelse/api/vllm/config/settings.py
wattelse/api/vllm/start.py
wattelse/api/vllm/stop.py
wattelse/api/wattelse_api.ipynb
wattelse/config_utils.py
wattelse/dashboard/dashboard.py
wattelse-1.2.3.dist-info/AUTHORS.txt
wattelse-1.2.3.dist-info/LICENSE.md
wattelse-1.2.3.dist-info/METADATA
wattelse-1.2.3.dist-info/WHEEL
wattelse-1.2.3.dist-info/RECORD
