Metadata-Version: 2.3
Name: wattelse
Version: 1.2.3
Summary: Flexible RAG
License: MPL 2.0
Author: Jérôme Picault
Author-email: jerome.picault@rte-france.com
Requires-Python: >=3.11,<3.13
Classifier: License :: Other/Proprietary License
Classifier: Programming Language :: Python :: 3
Classifier: Programming Language :: Python :: 3.11
Classifier: Programming Language :: Python :: 3.12
Requires-Dist: PyJWT (>=2.10.1,<3.0.0)
Requires-Dist: accelerate (>=1.6.0,<2.0.0)
Requires-Dist: bert-score (>=0.3.13,<0.4.0)
Requires-Dist: black (>=24.10.0,<25.0.0)
Requires-Dist: bs4 (>=0.0.2,<0.0.3)
Requires-Dist: chromadb (==0.5.11)
Requires-Dist: django (>=5.2,<6.0)
Requires-Dist: docxtpl (>=0.18.0,<0.19.0)
Requires-Dist: evaluate (>=0.4.3,<0.5.0)
Requires-Dist: fastapi (>=0.115.12,<0.116.0)
Requires-Dist: fschat (>=0.2.36,<0.3.0)
Requires-Dist: langchain (>=0.3.23,<0.4.0)
Requires-Dist: langchain-chroma (>=0.1.4,<0.2.0)
Requires-Dist: langchain-community (>=0.3.21,<0.4.0)
Requires-Dist: langchain-openai (>=0.3.12,<0.4.0)
Requires-Dist: llama-index-core (>=0.11.16,<0.12.0)
Requires-Dist: locust (>=2.34.1,<3.0.0)
Requires-Dist: loguru (>=0.7.3,<0.8.0)
Requires-Dist: mammoth (>=1.9.0,<2.0.0)
Requires-Dist: markdown (>=3.7,<4.0)
Requires-Dist: numpy (<2)
Requires-Dist: openai (>=1.72.0,<2.0.0)
Requires-Dist: openpyxl (>=3.1.5,<4.0.0)
Requires-Dist: pandas (>=2.2.3,<3.0.0)
Requires-Dist: plotly (>=5.24.1,<6.0.0)
Requires-Dist: pymupdf (>=1.25.5,<2.0.0)
Requires-Dist: pysqlite3-binary (>=0.5.4,<0.6.0)
Requires-Dist: python-docx (>=1.1.2,<2.0.0)
Requires-Dist: python-multipart (>=0.0.12,<0.0.13)
Requires-Dist: python-pptx (>=1.0.2,<2.0.0)
Requires-Dist: pyyaml (>=6.0.2,<7.0.0)
Requires-Dist: rank-bm25 (>=0.2.2,<0.3.0)
Requires-Dist: reportlab (>=4.3.1,<5.0.0)
Requires-Dist: scikit-learn (>=1.6.1,<2.0.0)
Requires-Dist: scipy (>=1.15.2,<2.0.0)
Requires-Dist: seaborn (>=0.13.2,<0.14.0)
Requires-Dist: sentence-transformers (>=3.4.1,<4.0.0)
Requires-Dist: spacy (<3.8)
Requires-Dist: sparqlwrapper (>=2.0.0,<3.0.0)
Requires-Dist: streamlit (>=1.44.1,<2.0.0)
Requires-Dist: tiktoken (>=0.7.0,<0.8.0)
Requires-Dist: torch (==2.4.0)
Requires-Dist: tqdm-joblib (>=0.0.4,<0.0.5)
Requires-Dist: tree_sitter (>=0.24.0,<0.25.0)
Requires-Dist: tree_sitter_languages (>=1.10.2,<2.0.0)
Requires-Dist: typer (>=0.12.5,<0.13.0)
Requires-Dist: unstructured (>=0.15.14,<0.16.0)
Requires-Dist: uvicorn (>=0.31.1,<0.32.0)
Requires-Dist: vllm (>=0.6.3,<0.7.0)
Requires-Dist: whitenoise (>=6.9.0,<7.0.0)
Requires-Dist: xlsx2html (>=0.6.2,<0.7.0)
